{
  "department": "Ngôn ngữ Anh",
  "program_code": "7220201",
  "academic_year": "2022",
  "total_credits": 140,
  "non_accumulated_credits": 5,
  "non_accumulated_program": "Chương trình Giáo dục Quốc phòng và an ninh",
  "courses": [
    {
      "category": "Kiến thức giáo dục đại cương",
      "total_credits": 53,
      "subcategories": [
        {
          "name": "Kiến thức bắt buộc",
          "total_credits": 35,
          "subjects": [
            {
              "code": "ENG183",
              "name": "Dẫn luận ngôn ngữ",
              "credits": 3,
              "prerequisites": [],
              "corequisites": []
            },
            {
              "code": "MAN116",
              "name": "Quản trị học",
              "credits": 3,
              "prerequisites": [],
              "corequisites": []
            },
            {
              "code": "PSY167",
              "name": "Tâm lý học ứng dụng",
              "credits": 3,
              "prerequisites": [],
              "corequisites": []
            },
            {
              "code": "SOS101",
              "name": "Cơ sở văn hóa Việt Nam",
              "credits": 3,
              "prerequisites": [],
              "corequisites": []
            },
            {
              "code": "CAP211",
              "name": "Nhập môn công nghệ thông tin",
              "credits": 3,
              "prerequisites": [],
              "corequisites": []
            },
            {
              "code": "POS103",
              "name": "Tư tưởng Hồ Chí Minh",
              "credits": 2,
              "prerequisites": [],
              "corequisites": []
            },
            {
              "code": "POS104",
              "name": "Triết học Mác - Lênin",
              "credits": 3,
              "prerequisites": [],
              "corequisites": []
            },
            {
              "code": "POS105",
              "name": "Kinh tế chính trị Mác - Lênin",
              "credits": 2,
              "prerequisites": [],
              "corequisites": []
            },
            {
              "code": "POS106",
              "name": "Chủ nghĩa xã hội khoa học",
              "credits": 2,
              "prerequisites": [],
              "corequisites": []
            },
            {
              "code": "POS107",
              "name": "Lịch sử Đảng Cộng sản Việt Nam",
              "credits": 2,
              "prerequisites": [],
              "corequisites": []
            },
            {
              "code": "LAW106",
              "name": "Pháp luật đại cương",
              "credits": 3,
              "prerequisites": [],
              "corequisites": []
            },
            {
              "code": "SKL115",
              "name": "Tư duy thiết kế dự án",
              "credits": 3,
              "prerequisites": [],
              "corequisites": []
            },
            {
              "code": "SKL116",
              "name": "Đổi mới sáng tạo và tư duy khởi nghiệp",
              "credits": 3,
              "prerequisites": ["SKL115"],
              "corequisites": []
            }
          ]
        },
        {
          "name": "Kiến thức tự chọn (Ngoại ngữ)",
          "total_credits": 18,
          "groups": [
            {
              "group_name": "Nhóm 1",
              "subjects": [
                {
                  "code": "JPC101",
                  "name": "Tiếng Nhật 1",
                  "credits": 3,
                  "prerequisites": [],
                  "corequisites": []
                },
                {
                  "code": "JPC102",
                  "name": "Tiếng Nhật 2",
                  "credits": 3,
                  "prerequisites": ["JPC101"],
                  "corequisites": []
                },
                {
                  "code": "JPC103",
                  "name": "Tiếng Nhật 3",
                  "credits": 3,
                  "prerequisites": ["JPC102"],
                  "corequisites": []
                },
                {
                  "code": "JPC104",
                  "name": "Tiếng Nhật 4",
                  "credits": 3,
                  "prerequisites": ["JPC103"],
                  "corequisites": []
                },
                {
                  "code": "JPC105",
                  "name": "Tiếng Nhật 5",
                  "credits": 3,
                  "prerequisites": ["JPC104"],
                  "corequisites": []
                },
                {
                  "code": "JPC106",
                  "name": "Tiếng Nhật 6",
                  "credits": 3,
                  "prerequisites": ["JPC105"],
                  "corequisites": []
                }
              ]
            },
            {
              "group_name": "Nhóm 2",
              "subjects": [
                {
                  "code": "CHN101",
                  "name": "Tiếng Trung 1",
                  "credits": 3,
                  "prerequisites": [],
                  "corequisites": []
                },
                {
                  "code": "CHN102",
                  "name": "Tiếng Trung 2",
                  "credits": 3,
                  "prerequisites": ["CHN101"],
                  "corequisites": []
                },
                {
                  "code": "CHN103",
                  "name": "Tiếng Trung 3",
                  "credits": 3,
                  "prerequisites": ["CHN102"],
                  "corequisites": []
                },
                {
                  "code": "CHN104",
                  "name": "Tiếng Trung 4",
                  "credits": 3,
                  "prerequisites": ["CHN103"],
                  "corequisites": []
                },
                {
                  "code": "CHN105",
                  "name": "Tiếng Trung 5",
                  "credits": 3,
                  "prerequisites": ["CHN104"],
                  "corequisites": []
                },
                {
                  "code": "CHN106",
                  "name": "Tiếng Trung 6",
                  "credits": 3,
                  "prerequisites": ["CHN105"],
                  "corequisites": []
                }
              ]
            },
            {
              "group_name": "Nhóm 3",
              "subjects": [
                {
                  "code": "FRE101",
                  "name": "Tiếng Pháp 1",
                  "credits": 3,
                  "prerequisites": [],
                  "corequisites": []
                },
                {
                  "code": "FRE102",
                  "name": "Tiếng Pháp 2",
                  "credits": 3,
                  "prerequisites": ["FRE101"],
                  "corequisites": []
                },
                {
                  "code": "FRE103",
                  "name": "Tiếng Pháp 3",
                  "credits": 3,
                  "prerequisites": ["FRE102"],
                  "corequisites": []
                },
                {
                  "code": "FRE104",
                  "name": "Tiếng Pháp 4",
                  "credits": 3,
                  "prerequisites": ["FRE103"],
                  "corequisites": []
                },
                {
                  "code": "FRE105",
                  "name": "Tiếng Pháp 5",
                  "credits": 3,
                  "prerequisites": ["FRE104"],
                  "corequisites": []
                },
                {
                  "code": "FRE106",
                  "name": "Tiếng Pháp 6",
                  "credits": 3,
                  "prerequisites": ["FRE105"],
                  "corequisites": []
                }
              ]
            },
            {
              "group_name": "Nhóm 4",
              "subjects": [
                {
                  "code": "KOR124",
                  "name": "Tiếng Hàn 1",
                  "credits": 3,
                  "prerequisites": [],
                  "corequisites": []
                },
                {
                  "code": "KOR125",
                  "name": "Tiếng Hàn 2",
                  "credits": 3,
                  "prerequisites": ["KOR124"],
                  "corequisites": []
                },
                {
                  "code": "KOR126",
                  "name": "Tiếng Hàn 3",
                  "credits": 3,
                  "prerequisites": ["KOR125"],
                  "corequisites": []
                },
                {
                  "code": "KOR127",
                  "name": "Tiếng Hàn 4",
                  "credits": 3,
                  "prerequisites": ["KOR126"],
                  "corequisites": []
                },
                {
                  "code": "KOR128",
                  "name": "Tiếng Hàn 5",
                  "credits": 3,
                  "prerequisites": ["KOR127"],
                  "corequisites": []
                },
                {
                  "code": "KOR129",
                  "name": "Tiếng Hàn 6",
                  "credits": 3,
                  "prerequisites": ["KOR128"],
                  "corequisites": []
                }
              ]
            }
          ]
        }
      ]
    },
    {
      "category": "Kiến thức giáo dục chuyên nghiệp",
      "total_credits": 87,
      "subcategories": [
        {
          "name": "Kiến thức bắt buộc",
          "total_credits": 75,
          "subjects": [
            {
              "code": "ENG111",
              "name": "Luyện ngữ âm tiếng Anh",
              "credits": 3,
              "prerequisites": [],
              "corequisites": []
            },
            {
              "code": "ENG181",
              "name": "Kỹ năng nghe, nói cơ bản",
              "credits": 3,
              "prerequisites": [],
              "corequisites": []
            },
            {
              "code": "ENG184",
              "name": "Kỹ năng nghe, nói trung cấp",
              "credits": 3,
              "prerequisites": ["ENG181"],
              "corequisites": []
            },
            {
              "code": "ENG185",
              "name": "Kỹ năng nghe nâng cao",
              "credits": 3,
              "prerequisites": ["ENG184"],
              "corequisites": []
            },
            {
              "code": "ENG151",
              "name": "Kỹ năng ghi chép",
              "credits": 3,
              "prerequisites": ["ENG185"],
              "corequisites": []
            },
            {
              "code": "ENG152",
              "name": "Kỹ năng thảo luận",
              "credits": 3,
              "prerequisites": ["ENG184"],
              "corequisites": []
            },
            {
              "code": "ENG154",
              "name": "Kỹ năng tranh luận",
              "credits": 3,
              "prerequisites": ["ENG152"],
              "corequisites": []
            },
            {
              "code": "ENG182",
              "name": "Kỹ năng đọc cơ bản",
              "credits": 3,
              "prerequisites": [],
              "corequisites": []
            },
            {
              "code": "ENG186",
              "name": "Kỹ năng đọc trung cấp",
              "credits": 3,
              "prerequisites": ["ENG182"],
              "corequisites": []
            },
            {
              "code": "ENG187",
              "name": "Kỹ năng đọc nâng cao",
              "credits": 3,
              "prerequisites": ["ENG186"],
              "corequisites": []
            },
            {
              "code": "ENG188",
              "name": "Kỹ năng viết câu văn",
              "credits": 3,
              "prerequisites": [],
              "corequisites": []
            },
            {
              "code": "ENG189",
              "name": "Kỹ năng viết đoạn văn",
              "credits": 3,
              "prerequisites": ["ENG188"],
              "corequisites": []
            },
            {
              "code": "ENG190",
              "name": "Kỹ năng viết bài luận",
              "credits": 3,
              "prerequisites": ["ENG189"],
              "corequisites": []
            },
            {
              "code": "ENG191",
              "name": "Ngữ pháp tiếng Anh",
              "credits": 3,
              "prerequisites": [],
              "corequisites": []
            },
            {
              "code": "ENG153",
              "name": "Kỹ năng thuyết trình",
              "credits": 3,
              "prerequisites": ["ENG152"],
              "corequisites": []
            },
            {
              "code": "ENG192",
              "name": "Kỹ năng biên dịch",
              "credits": 3,
              "prerequisites": [],
              "corequisites": []
            },
            {
              "code": "ENG193",
              "name": "Kỹ năng phiên dịch",
              "credits": 3,
              "prerequisites": [],
              "corequisites": []
            },
            {
              "code": "ENG194",
              "name": "Âm vị học và hình thái học",
              "credits": 3,
              "prerequisites": [],
              "corequisites": []
            },
            {
              "code": "ENG195",
              "name": "Cú pháp học và ngữ nghĩa học",
              "credits": 3,
              "prerequisites": [],
              "corequisites": []
            },
            {
              "code": "ENG171",
              "name": "Văn hóa và xã hội Anh, Mỹ",
              "credits": 3,
              "prerequisites": [],
              "corequisites": []
            },
            {
              "code": "ENG170",
              "name": "Văn học Anh, Mỹ",
              "credits": 3,
              "prerequisites": [],
              "corequisites": []
            },
            {
              "code": "ENG196",
              "name": "Kỹ năng tổ chức sự kiện",
              "credits": 3,
              "prerequisites": [],
              "corequisites": []
            },
            {
              "code": "ENG149",
              "name": "Biên dịch thương mại",
              "credits": 3,
              "prerequisites": [],
              "corequisites": []
            },
            {
              "code": "ENG114",
              "name": "Kỹ năng thi tiếng Anh quốc tế",
              "credits": 3,
              "prerequisites": [],
              "corequisites": []
            },
            {
              "code": "ENG576",
              "name": "Thực tập tốt nghiệp ngành Ngôn ngữ Anh",
              "credits": 3,
              "prerequisites": [],
              "corequisites": []
            }
          ]
        },
        {
          "name": "Kiến thức tự chọn",
          "total_credits": 12,
          "groups": [
            {
              "group_name": "Tiếng Anh thương mại",
              "subjects": [
                {
                  "code": "ENG197",
                  "name": "Tiếp thị cơ bản",
                  "credits": 3,
                  "prerequisites": [],
                  "corequisites": []
                },
                {
                  "code": "ENG198",
                  "name": "Kỹ năng giao tiếp trong thương mại",
                  "credits": 3,
                  "prerequisites": [],
                  "corequisites": []
                },
                {
                  "code": "ENG199",
                  "name": "Nguyên tắc quản lý kinh doanh cơ bản",
                  "credits": 3,
                  "prerequisites": [],
                  "corequisites": []
                },
                {
                  "code": "MAN2053",
                  "name": "Quản trị hành chính văn phòng",
                  "credits": 3,
                  "prerequisites": ["MAN116"],
                  "corequisites": []
                }
              ]
            },
            {
              "group_name": "Biên, phiên dịch tiếng Anh",
              "subjects": [
                {
                  "code": "ENG1001",
                  "name": "Lý thuyết dịch thuật",
                  "credits": 3,
                  "prerequisites": [],
                  "corequisites": []
                },
                {
                  "code": "ENG1006",
                  "name": "Công nghệ thông tin trong biên phiên dịch",
                  "credits": 3,
                  "prerequisites": [],
                  "corequisites": []
                },
                {
                  "code": "ENG1002",
                  "name": "Biên dịch báo chí",
                  "credits": 3,
                  "prerequisites": [],
                  "corequisites": []
                },
                {
                  "code": "ENG156",
                  "name": "Phiên dịch nâng cao",
                  "credits": 3,
                  "prerequisites": [],
                  "corequisites": []
                }
              ]
            },
            {
              "group_name": "Phương pháp giảng dạy tiếng Anh",
              "subjects": [
                {
                  "code": "ENG172",
                  "name": "Lý luận giảng dạy tiếng Anh",
                  "credits": 3,
                  "prerequisites": [],
                  "corequisites": []
                },
                {
                  "code": "ENG173",
                  "name": "Kỹ thuật giảng dạy tiếng Anh",
                  "credits": 3,
                  "prerequisites": [],
                  "corequisites": []
                },
                {
                  "code": "ENG175",
                  "name": "Phương pháp giảng dạy tiếng Anh cho thiếu nhi",
                  "credits": 3,
                  "prerequisites": [],
                  "corequisites": []
                },
                {
                  "code": "ENG174",
                  "name": "Thực hành giảng dạy tiếng Anh",
                  "credits": 3,
                  "prerequisites": [],
                  "corequisites": []
                }
              ]
            },
            {
              "group_name": "Tiếng Anh du lịch, khách sạn, nhà hàng",
              "subjects": [
                {
                  "code": "ENG1003",
                  "name": "Tổng quan du lịch, khách sạn, nhà hàng",
                  "credits": 3,
                  "prerequisites": [],
                  "corequisites": []
                },
                {
                  "code": "ENG129",
                  "name": "Kỹ năng hướng dẫn du lịch",
                  "credits": 3,
                  "prerequisites": [],
                  "corequisites": []
                },
                {
                  "code": "ENG1004",
                  "name": "Nghiệp vụ lễ tân khách sạn",
                  "credits": 3,
                  "prerequisites": [],
                  "corequisites": []
                },
                {
                  "code": "ENG1005",
                  "name": "Tiếp thị du lịch, khách sạn, nhà hàng",
                  "credits": 3,
                  "prerequisites": [],
                  "corequisites": []
                }
              ]
            },
            {
              "group_name": "Khóa luận tốt nghiệp",
              "subjects": [
                {
                  "code": "ENG477",
                  "name": "Khóa luận tốt nghiệp ngành Ngôn ngữ Anh",
                  "credits": 12,
                  "prerequisites": [],
                  "corequisites": []
                }
              ]
            }
          ]
        }
      ]
    },
    {
      "category": "Kiến thức không tích lũy",
      "total_credits": 5,
      "subcategories": [
        {
          "name": "Giáo dục thể chất",
          "total_credits": 5,
          "note": "Tự chọn 1 trong 5 nhóm",
          "groups": [
            {
              "group_name": "Nhóm 1",
              "subjects": [
                {
                  "code": "PHT304",
                  "name": "Bóng chuyền 1",
                  "credits": 2,
                  "prerequisites": [],
                  "corequisites": []
                },
                {
                  "code": "PHT305",
                  "name": "Bóng chuyền 2",
                  "credits": 2,
                  "prerequisites": ["PHT304"],
                  "corequisites": []
                },
                {
                  "code": "PHT306",
                  "name": "Bóng chuyền 3",
                  "credits": 1,
                  "prerequisites": ["PHT305"],
                  "corequisites": []
                }
              ]
            },
            {
              "group_name": "Nhóm 2",
              "subjects": [
                {
                  "code": "PHT307",
                  "name": "Bóng rổ 1",
                  "credits": 2,
                  "prerequisites": [],
                  "corequisites": []
                },
                {
                  "code": "PHT308",
                  "name": "Bóng rổ 2",
                  "credits": 2,
                  "prerequisites": ["PHT307"],
                  "corequisites": []
                },
                {
                  "code": "PHT309",
                  "name": "Bóng rổ 3",
                  "credits": 1,
                  "prerequisites": ["PHT308"],
                  "corequisites": []
                }
              ]
            },
            {
              "group_name": "Nhóm 3",
              "subjects": [
                {
                  "code": "PHT310",
                  "name": "Thể hình - Thẩm mỹ 1",
                  "credits": 2,
                  "prerequisites": [],
                  "corequisites": []
                },
                {
                  "code": "PHT311",
                  "name": "Thể hình - Thẩm mỹ 2",
                  "credits": 2,
                  "prerequisites": ["PHT310"],
                  "corequisites": []
                },
                {
                  "code": "PHT312",
                  "name": "Thể hình - Thẩm mỹ 3",
                  "credits": 1,
                  "prerequisites": ["PHT311"],
                  "corequisites": []
                }
              ]
            },
            {
              "group_name": "Nhóm 4",
              "subjects": [
                {
                  "code": "PHT313",
                  "name": "Vovinam 1",
                  "credits": 2,
                  "prerequisites": [],
                  "corequisites": []
                },
                {
                  "code": "PHT314",
                  "name": "Vovinam 2",
                  "credits": 2,
                  "prerequisites": ["PHT313"],
                  "corequisites": []
                },
                {
                  "code": "PHT315",
                  "name": "Vovinam 3",
                  "credits": 1,
                  "prerequisites": ["PHT314"],
                  "corequisites": []
                }
              ]
            },
            {
              "group_name": "Nhóm 5",
              "subjects": [
                {
                  "code": "PHT316",
                  "name": "Bóng đá 1",
                  "credits": 2,
                  "prerequisites": [],
                  "corequisites": []
                },
                {
                  "code": "PHT317",
                  "name": "Bóng đá 2",
                  "credits": 2,
                  "prerequisites": ["PHT316"],
                  "corequisites": []
                },
                {
                  "code": "PHT318",
                  "name": "Bóng đá 3",
                  "credits": 1,
                  "prerequisites": ["PHT317"],
                  "corequisites": []
                }
              ]
            }
          ]
        },
        {
          "name": "Chương trình Giáo dục quốc phòng và an ninh",
          "note": "Bắt buộc, không tích lũy",
          "subjects": [
            {
              "code": "NDF108",
              "name": "Quốc phòng, an ninh 1",
              "credits": 0,
              "prerequisites": [],
              "corequisites": []
            },
            {
              "code": "NDF109",
              "name": "Quốc phòng, an ninh 2",
              "credits": 0,
              "prerequisites": [],
              "corequisites": []
            },
            {
              "code": "NDF210",
              "name": "Quốc phòng, an ninh 3",
              "credits": 0,
              "prerequisites": [],
              "corequisites": []
            },
            {
              "code": "NDF211",
              "name": "Quốc phòng, an ninh 4",
              "credits": 0,
              "prerequisites": [],
              "corequisites": []
            }
          ]
        }
      ]
    }
  ],
  "additional_info": {
    "decision_number": "1488/QĐ-ĐKC",
    "decision_date": "15 tháng 6 năm 2022",
    "signed_by": "GS.TS. Nguyễn Trung Kiên",
    "note": "Sinh viên được xét điều kiện Thực tập, Khóa luận tốt nghiệp theo quy định của Khoa."
  }
}